babbleon/__init__.py
babbleon/cli.py
babbleon/config.py
babbleon/prompts/translator_json.md
babbleon/prompts/translator_toml.md
babbleon/templates/babbleon.json
babbleon/templates/reference.toml
babbleon/translate.py
babbleon-0.1.5.dist-info/LICENSE
babbleon-0.1.5.dist-info/METADATA
babbleon-0.1.5.dist-info/WHEEL
babbleon-0.1.5.dist-info/entry_points.txt
babbleon-0.1.5.dist-info/RECORD
